[
    {
        "title": "What is Best First Search?",
        "category": "Search Algorithms",
        "content": "Best First Search is a searching algorithm that uses a priority queue and heuristic search to find the shortest path from the initial state to the goal state.",
        "subtopics": [
            "What are Searching algorithms?",
            "Comparison of Best First Search Algorithm",
            "Example of Best First Search",
            "Advantages and Disadvantages of Best First Search Algorithm"
        ]
    },
    {
        "title": "Supervised Learning",
        "category": "Machine Learning (ML) Algorithms",
        "content": "Supervised Learning is an ML technique where a model learns from labeled data. It is used for classification and regression tasks.",
        "subtopics": [
            "Types of Supervised Learning",
            "Classification vs Regression",
            "Example: Spam Email Detection"
        ]
    }
]
